google/cloud/cloudsecuritycompliance/__init__.py
google/cloud/cloudsecuritycompliance/gapic_version.py
google/cloud/cloudsecuritycompliance/py.typed
google/cloud/cloudsecuritycompliance_v1/__init__.py
google/cloud/cloudsecuritycompliance_v1/gapic_metadata.json
google/cloud/cloudsecuritycompliance_v1/gapic_version.py
google/cloud/cloudsecuritycompliance_v1/py.typed
google/cloud/cloudsecuritycompliance_v1/services/__init__.py
google/cloud/cloudsecuritycompliance_v1/services/audit/__init__.py
google/cloud/cloudsecuritycompliance_v1/services/audit/async_client.py
google/cloud/cloudsecuritycompliance_v1/services/audit/client.py
google/cloud/cloudsecuritycompliance_v1/services/audit/pagers.py
google/cloud/cloudsecuritycompliance_v1/services/audit/transports/__init__.py
google/cloud/cloudsecuritycompliance_v1/services/audit/transports/base.py
google/cloud/cloudsecuritycompliance_v1/services/audit/transports/grpc.py
google/cloud/cloudsecuritycompliance_v1/services/audit/transports/grpc_asyncio.py
google/cloud/cloudsecuritycompliance_v1/services/audit/transports/rest.py
google/cloud/cloudsecuritycompliance_v1/services/audit/transports/rest_base.py
google/cloud/cloudsecuritycompliance_v1/services/cm_enrollment_service/__init__.py
google/cloud/cloudsecuritycompliance_v1/services/cm_enrollment_service/async_client.py
google/cloud/cloudsecuritycompliance_v1/services/cm_enrollment_service/client.py
google/cloud/cloudsecuritycompliance_v1/services/cm_enrollment_service/transports/__init__.py
google/cloud/cloudsecuritycompliance_v1/services/cm_enrollment_service/transports/base.py
google/cloud/cloudsecuritycompliance_v1/services/cm_enrollment_service/transports/grpc.py
google/cloud/cloudsecuritycompliance_v1/services/cm_enrollment_service/transports/grpc_asyncio.py
google/cloud/cloudsecuritycompliance_v1/services/cm_enrollment_service/transports/rest.py
google/cloud/cloudsecuritycompliance_v1/services/cm_enrollment_service/transports/rest_base.py
google_cloud_cloudsecuritycompliance-0.5.0.dist-info/licenses/LICENSE
google_cloud_cloudsecuritycompliance-0.5.0.dist-info/METADATA
google_cloud_cloudsecuritycompliance-0.5.0.dist-info/WHEEL
google_cloud_cloudsecuritycompliance-0.5.0.dist-info/top_level.txt
google_cloud_cloudsecuritycompliance-0.5.0.dist-info/RECORD
